pre_commit_mirror_maker/__init__.py
pre_commit_mirror_maker/languages.py
pre_commit_mirror_maker/main.py
pre_commit_mirror_maker/make_repo.py
pre_commit_mirror_maker/all/.pre-commit-hooks.yaml
pre_commit_mirror_maker/all/.version
pre_commit_mirror_maker/node/.npmignore
pre_commit_mirror_maker/node/package.json
pre_commit_mirror_maker/python/setup.py
pre_commit_mirror_maker/ruby/pre_commit_fake_gem.gemspec
pre_commit_mirror_maker/rust/Cargo.toml
pre_commit_mirror_maker/rust/main.rs
pre_commit_mirror_maker-1.10.0.dist-info/LICENSE
pre_commit_mirror_maker-1.10.0.dist-info/METADATA
pre_commit_mirror_maker-1.10.0.dist-info/WHEEL
pre_commit_mirror_maker-1.10.0.dist-info/entry_points.txt
pre_commit_mirror_maker-1.10.0.dist-info/top_level.txt
pre_commit_mirror_maker-1.10.0.dist-info/RECORD
