Metadata-Version: 2.1
Name: pre-commit-mirror-maker
Version: 1.10.0
Summary: Scripts for creating mirror repositories that do not have .pre-commit-hooks.yaml
Home-page: https://github.com/pre-commit/pre-commit-mirror-maker
Author: Anthony Sottile
Author-email: asottile@umich.edu
License: MIT
Platform: all
Classifier: License :: OSI Approved :: MIT License
Classifier: Programming Language :: Python :: 3
Classifier: Programming Language :: Python :: 3 :: Only
Classifier: Programming Language :: Python :: Implementation :: CPython
Classifier: Programming Language :: Python :: Implementation :: PyPy
Requires-Python: >=3.9
License-File: LICENSE
Requires-Dist: packaging
